{
  "type": "store_hot_products",
  "schema": ["排名","商品名","笔数","数量"],
  "今": [
    [1,\[芬必得]布洛芬缓释胶囊 0.3g*10粒*2板/盒",3,3],
    [2,\[农夫山泉]饮用天然水 550ml/瓶",3,6],
    [3,\[维福佳]维生素 C片 0.1g*100片/瓶",2,2],
    [4,\[三金]西瓜霜润喉片 0.6g*36片/盒",2,2],
    [5,\[葵花]人工牛黄甲硝唑胶囊 12粒*2板/盒",2,2],
    [6,"艾纳香 咽立爽口含滴丸 0.025g*60丸瓶/盒",2,2],
    [7,\[晶明]更昔洛韦滴眼液 (8ml:8mg)*8ml/瓶/盒",1,1],
    [8,\[毓婷]左炔诺孕酮片 (72小时紧急避孕药)0.75mg*2片/板/盒",1,1],
    [9,\[整肠生]地衣芽孢杆菌活菌胶囊 0.25g*20粒/瓶/盒",1,1],
    [10,\[金双歧]双歧杆菌乳杆菌三联活菌片 0.5g*12片*3板/盒",1,1],
    [11,"金毓婷 左炔诺孕酮片 1.5mg*2片/盒",1,1],
    [12,"酒川芎 10克",null,null]
  ],
  "周": [
    [1,\[芬必得]布洛芬缓释胶囊 0.3g*10粒*2板/盒",19,19],
    [2,\[丹南泰]和胃整肠丸 0.2g*50丸/瓶/盒",16,16],
    [3,\[农夫山泉]饮用天然水 550ml/瓶",14,35],
    [4,\[金双歧]双歧杆菌乳杆菌三联活菌片 0.5g*12片*3板/盒",12,14],
    [5,\[都乐]金嗓子喉片 2g*6片*2板/盒",12,12],
    [6,\[海氏海诺]医用棉签 10cm*50支/袋",12,14]
  ],
  "月": [
    [1,"芬必得 布洛芬缓释胶囊 0.3g*20粒/盒",106,106],
    [2,\[丹南泰]和胃整肠丸 0.2g*50丸/瓶/盒",59,59],
    [3,\[999]感冒灵颗粒 10g*9袋/盒",53,53],
    [4,\[金双歧]双歧杆菌乳杆菌三联活菌片 0.5g*12片*3板/盒",43,49],
    [5,\[农夫山泉]饮用天然水 550ml/瓶",42,79],
    [6,\[都乐]金嗓子喉片 2g*6片*2板/盒",37,37]
  ],
  "昨": [
    [1,\[丹南泰]和胃整肠丸 0.2g*50丸/瓶/盒",4,4],
    [2,\[康恩贝]肠炎宁片 0.42g*12片*2板/盒",3,3],
    [3,\[金双歧]双歧杆菌乳杆菌三联活菌片 0.5g*12片*3板/盒",3,3],
    [4,\[恩威]洁尔阴洗液 160ml/瓶",2,2],
    [5,"连花 连花清瘟胶囊 0.35g*36粒/盒",2,3],
    [6,\[苏春]珍珠明目滴眼液 8ml/支/盒",2,2]
  ]
}